LICENSE
README.md
setup.py
CVE_2015_7297.egg-info/PKG-INFO
CVE_2015_7297.egg-info/SOURCES.txt
CVE_2015_7297.egg-info/dependency_links.txt
CVE_2015_7297.egg-info/entry_points.txt
CVE_2015_7297.egg-info/requires.txt
CVE_2015_7297.egg-info/top_level.txt
cve20157297/__init__.py
cve20157297/main.py
cve20157297/includes/__init__.py
cve20157297/includes/bot.py
cve20157297/includes/filereader.py
cve20157297/includes/scan.py
cve20157297/includes/writefile.py
cve20157297/utils/__init__.py
cve20157297/utils/configure.py
cve20157297/utils/const.py
cve20157297/utils/helpers.py
cve20157297/utils/status.py